m2g/__init__.py
m2g/graph.py
m2g/preproc.py
m2g/register.py
m2g/track.py
m2g/scripts/__init__.py
m2g/scripts/m2g_bids.py
m2g/scripts/m2g_cloud.py
m2g/scripts/m2g_dwi_pipeline.py
m2g/stats/__init__.py
m2g/stats/qa_fast.py
m2g/stats/qa_reg.py
m2g/stats/qa_skullstrip.py
m2g/stats/qa_tensor.py
m2g/stats/qa_tractography.py
m2g/utils/__init__.py
m2g/utils/cloud_utils.py
m2g/utils/gen_utils.py
m2g/utils/qa_utils.py
m2g/utils/reg_utils.py
m2g-0.3.0.dist-info/LICENSE.txt
m2g-0.3.0.dist-info/METADATA
m2g-0.3.0.dist-info/WHEEL
m2g-0.3.0.dist-info/entry_points.txt
m2g-0.3.0.dist-info/top_level.txt
m2g-0.3.0.dist-info/RECORD
