Metadata-Version: 2.1
Name: m2g
Version: 0.3.0
Summary: Neuro Data MRI to Graphs Pipeline
Home-page: https://github.com/neurodata/m2g
Author: Derek Pisner, Alex Loftus, Greg Kiar, Eric Bridgeford, and Will Gray Roncal
Author-email: dpisner@utexas.edu, aloftus2@jhu.edu, gkiar@jhu.edu, wgr@jhu.edu, ebridge2@jhu.edu
License: UNKNOWN
Download-URL: https://github.com/neurodata/m2g/tarball/0.3.0
Keywords: connectome,mri,pipeline
Platform: UNKNOWN
Classifier: Programming Language :: Python :: 3.6
Requires-Python: >=3.6
Requires-Dist: nibabel
Requires-Dist: numpy
Requires-Dist: dipy (>=1.0.0)
Requires-Dist: scipy
Requires-Dist: boto3
Requires-Dist: awscli
Requires-Dist: matplotlib
Requires-Dist: nilearn
Requires-Dist: vtk
Requires-Dist: pyvtk
Requires-Dist: fury
Requires-Dist: requests
Requires-Dist: plotly
Requires-Dist: pybids (>=0.9.0)
Requires-Dist: scikit-image
Requires-Dist: networkx (>=2.4)
Requires-Dist: configparser (>=3.7.4)
Requires-Dist: pytest
